AriaQuanta/__init__.py
AriaQuanta/_utils.py
AriaQuanta/config.py
AriaQuanta/algorithms/__init__.py
AriaQuanta/algorithms/dj_algorithm.py
AriaQuanta/algorithms/grover_algorithm.py
AriaQuanta/algorithms/iqft_algorithm.py
AriaQuanta/algorithms/qft_algorithm.py
AriaQuanta/algorithms/qpe_algorithm.py
AriaQuanta/algorithms/shor_algorithm.py
AriaQuanta/algorithms/vqe_algorithm.py
AriaQuanta/algorithms/vqe_algorithm_sample.py
AriaQuanta/aqc/__init__.py
AriaQuanta/aqc/circuit.py
AriaQuanta/aqc/measure.py
AriaQuanta/aqc/noise.py
AriaQuanta/aqc/operations.py
AriaQuanta/aqc/qubit.py
AriaQuanta/aqc/visualization.py
AriaQuanta/aqc/gatelibrary/__init__.py
AriaQuanta/aqc/gatelibrary/arxived_gatetriple.py
AriaQuanta/aqc/gatelibrary/gatecontrol.py
AriaQuanta/aqc/gatelibrary/gatecontroln.py
AriaQuanta/aqc/gatelibrary/gatecustom.py
AriaQuanta/aqc/gatelibrary/gatedouble.py
AriaQuanta/aqc/gatelibrary/gatesingle.py
AriaQuanta/backend/__init__.py
AriaQuanta/backend/job.py
AriaQuanta/backend/result.py
AriaQuanta/backend/simulator.py
ariaquantum-0.1.9.dist-info/licenses/LICENSE
ariaquantum-0.1.9.dist-info/METADATA
ariaquantum-0.1.9.dist-info/WHEEL
ariaquantum-0.1.9.dist-info/top_level.txt
ariaquantum-0.1.9.dist-info/RECORD
