Metadata-Version: 2.4
Name: AriaQuantum
Version: 0.1.9
Summary: A quantum computing library
Home-page: https://github.com/khaterehazizi/AriaQuanta.git
Author: khaterehazizi
Author-email: kht.azizi@gmail.com
License: Apache License 2.0
Classifier: Programming Language :: Python :: 3
Classifier: License :: OSI Approved :: Apache Software License
Classifier: Operating System :: OS Independent
Requires-Python: >=3.7
License-File: LICENSE
Requires-Dist: matplotlib>=3.10.0
Requires-Dist: numpy>=1.26.4
Requires-Dist: scipy>=1.15.1
Requires-Dist: pandas>=2.0.1
Dynamic: author
Dynamic: author-email
Dynamic: classifier
Dynamic: description
Dynamic: description-content-type
Dynamic: home-page
Dynamic: license
Dynamic: license-file
Dynamic: requires-dist
Dynamic: requires-python
Dynamic: summary
